LICENSE
klee/__init__.py
klee/build.py
klee/cases.py
klee/claims.py
klee/commands.py
klee/files.py
klee/insights.py
klee/internal.py
klee/plans/__init__.py
klee/plans/legacy.py
klee/plans/mpe_test.py
klee/pyt/local.py
klee/pyt/shared.py
klee/pyt/staging.py
klee/resource/.gitignore
klee/resource/cron-nightly.yml
klee/resource/relock_redeploy.yml
klee/resource/test_engine.yml
klee/test.py
klee/utils/__init__.py
klee/utils/sync_pipenv.py
klee/utils/v1_redeploy.py
rialtic_klee_py-0.0.16.dist-info/entry_points.txt
rialtic_klee_py-0.0.16.dist-info/LICENSE
rialtic_klee_py-0.0.16.dist-info/WHEEL
rialtic_klee_py-0.0.16.dist-info/METADATA
rialtic_klee_py-0.0.16.dist-info/RECORD
