Metadata-Version: 2.1
Name: rialtic-klee-py
Version: 0.0.16
Summary: Internal workflow/testing utility
Home-page: https://github.com/rialtic-community/rialtic-klee-py
License: Apache-2.0
Keywords: rialtic,insight,engine,test-library
Author: Rialtic
Author-email: engines.data@rialtic.io
Requires-Python: >=3.7,<4.0
Classifier: License :: OSI Approved :: Apache Software License
Classifier: Operating System :: OS Independent
Classifier: Programming Language :: Python :: 3
Classifier: Programming Language :: Python :: 3.10
Classifier: Programming Language :: Python :: 3.7
Classifier: Programming Language :: Python :: 3.8
Classifier: Programming Language :: Python :: 3.9
Classifier: Topic :: Software Development :: Libraries
Requires-Dist: PyGithub (>=1.55,<2.0)
Requires-Dist: click (>=8.0.3,<9.0.0)
Requires-Dist: fhir.resources (>=6.1.0,<7.0.0)
Requires-Dist: insight-engine-schema-python (>=0,<1)
Requires-Dist: pytest (>=6.2.5,<7.0.0)
Requires-Dist: pytest-html (>=3.1.1,<4.0.0)
Requires-Dist: python-dotenv (>=0.19.2,<0.20.0)
Requires-Dist: requests (>=2.26,<3.0)
Project-URL: Bug Tracker, https://github.com/rialtic-community/rialtic-klee-py
Project-URL: Repository, https://github.com/rialtic-community/rialtic-klee-py
